marketspec/__init__.py
marketspec/py.typed
marketspec/registry.py
marketspec/types.py
marketspec/unified.py
marketspec/exchanges/__init__.py
marketspec/exchanges/binance.py
marketspec/exchanges/bybit.py
marketspec-1.0.1.dist-info/METADATA
marketspec-1.0.1.dist-info/WHEEL
marketspec-1.0.1.dist-info/licenses/LICENSE
marketspec-1.0.1.dist-info/RECORD
