Metadata-Version: 2.4
Name: marketspec
Version: 1.0.1
Summary: Unified instrument spec parser and venue symbol resolver for crypto markets
Author: QuantFolks
License: MIT
License-File: LICENSE
Classifier: Development Status :: 4 - Beta
Classifier: Intended Audience :: Developers
Classifier: License :: OSI Approved :: MIT License
Classifier: Programming Language :: Python :: 3
Classifier: Programming Language :: Python :: 3 :: Only
Classifier: Topic :: Software Development :: Libraries
Classifier: Typing :: Typed
Requires-Python: >=3.9
